
{
"item": {
  "head": "ئامۆزا گیان",
  "singer": "شەهێن تاڵەبانی",
  "audio": "https://drive.google.com/uc?export=download&id=1BqhyW9rlAQKJhFfcuFdPMvLjFPKEiHNL",
  "lg": ["هەر دەڕۆم دەڕۆم دڵم ئەلەرزێ ئامۆزا گیان",
	"چۆن بە جێت بێڵم یار گەردن بەرزێ ئامۆزا گیان",
	"ئامۆزا تۆ باڵابەرزی ئامۆزا تۆ بۆ من فەڕزی",
	"ئامۆزا تاقە گوڵەکەم نەونەمام فێنکی دڵەکەم",
	"خۆرەتاوم خوێ دیەی پڕ دەردە ئامۆزا گیان",
	"نەسیمم شنەی هەناسەی سەردە ئامۆزا گیان",
	"شەماڵ بێنە بۆم عەتری زوڵفەکەی ئامۆزا گیان",
	"وەختە بمرم بۆ دیدە مەستەکەی ئامۆزا گیان"]
}
}
